work_concentrator/__init__.py
work_concentrator/work_concentrator.py
work_concentrator/notification/__init__.py
work_concentrator/notification/notification.py
pomodoro_DEN_ik-0.0.2.dist-info/LICENSE
pomodoro_DEN_ik-0.0.2.dist-info/METADATA
pomodoro_DEN_ik-0.0.2.dist-info/WHEEL
pomodoro_DEN_ik-0.0.2.dist-info/entry_points.txt
pomodoro_DEN_ik-0.0.2.dist-info/top_level.txt
pomodoro_DEN_ik-0.0.2.dist-info/RECORD
