Metadata-Version: 2.1
Name: pomodoro-DEN-ik
Version: 0.0.2
Summary: Simple concentrator based on pomodoro technique
Home-page: https://github.com/DarkDream99/WorkConcentrator
Author: Denys Zaluzhnyi
Author-email: denys.zaluzhnyi@gmail.com
License: UNKNOWN
Platform: UNKNOWN
Classifier: Topic :: Home Automation
Classifier: Programming Language :: Python :: 3
Classifier: License :: OSI Approved :: MIT License
Classifier: Operating System :: OS Independent
Requires-Python: >=3.6
Requires-Dist: py-notifier
